agentlab/__init__.py
agentlab/client.py
agentlab/converters.py
agentlab/exceptions.py
agentlab/models.py
agentlab/py.typed
agentlab/proto/__init__.py
agentlab/proto/agentlab/__init__.py
agentlab/proto/agentlab/agent/v1/__init__.py
agentlab/proto/agentlab/agent/v1/agent_pb2.py
agentlab/proto/agentlab/agent/v1/agent_service_connect.py
agentlab/proto/agentlab/agent/v1/agent_service_pb2.py
agentlab/proto/agentlab/analysis/__init__.py
agentlab/proto/agentlab/analysis/v1/__init__.py
agentlab/proto/agentlab/analysis/v1/analysis_service_connect.py
agentlab/proto/agentlab/analysis/v1/analysis_service_pb2.py
agentlab/proto/agentlab/evaluations/__init__.py
agentlab/proto/agentlab/evaluations/v1/__init__.py
agentlab/proto/agentlab/evaluations/v1/evaluation_connect.py
agentlab/proto/agentlab/evaluations/v1/evaluation_pb2.py
agentlab/proto/agentlab/iam/__init__.py
agentlab/proto/agentlab/iam/v1/__init__.py
agentlab/proto/agentlab/iam/v1/iam_service_connect.py
agentlab/proto/agentlab/iam/v1/iam_service_pb2.py
agentlab/proto/agentlab/iam/v1/membership_pb2.py
agentlab/proto/agentlab/organizations/v1/organization_pb2.py
agentlab/proto/agentlab/organizations/v1/organization_service_connect.py
agentlab/proto/agentlab/organizations/v1/organization_service_pb2.py
agentlab/proto/agentlab/projects/v1/project_pb2.py
agentlab/proto/agentlab/projects/v1/project_service_connect.py
agentlab/proto/agentlab/projects/v1/project_service_pb2.py
agentlab/proto/agentlab/testdatasets/v1/test_pb2.py
agentlab/proto/agentlab/testdatasets/v1/testdataset_pb2.py
agentlab/proto/agentlab/testdatasets/v1/testdataset_service_connect.py
agentlab/proto/agentlab/testdatasets/v1/testdataset_service_pb2.py
agentlab/validate/__init__.py
agentlab/validate/validate_pb2.py
agentlab_py-0.6.1.dist-info/licenses/LICENSE
agentlab_py-0.6.1.dist-info/METADATA
agentlab_py-0.6.1.dist-info/WHEEL
agentlab_py-0.6.1.dist-info/top_level.txt
agentlab_py-0.6.1.dist-info/RECORD
