Metadata-Version: 2.4
Name: agentlab-py
Version: 0.6.1
Summary: Python client library for the AgentLab evaluation platform using Connect RPC
Author-email: VectorLabs <info@vectorlabs.cz>
Maintainer-email: VectorLabs <info@vectorlabs.cz>
License: MIT
Project-URL: Homepage, https://github.com/VectorLabsCZ/agentlab-py
Project-URL: Documentation, https://github.com/VectorLabsCZ/agentlab-py#readme
Project-URL: Repository, https://github.com/VectorLabsCZ/agentlab-py
Project-URL: Issues, https://github.com/VectorLabsCZ/agentlab-py/issues
Keywords: agentlab,evaluation,ai,ml,rpc,connect,protobuf
Classifier: Development Status :: 3 - Alpha
Classifier: Intended Audience :: Developers
Classifier: License :: OSI Approved :: MIT License
Classifier: Operating System :: OS Independent
Classifier: Programming Language :: Python :: 3
Classifier: Programming Language :: Python :: 3.10
Classifier: Programming Language :: Python :: 3.11
Classifier: Programming Language :: Python :: 3.12
Classifier: Topic :: Software Development :: Libraries :: Python Modules
Classifier: Topic :: Scientific/Engineering :: Artificial Intelligence
Requires-Python: >=3.10
License-File: LICENSE
Requires-Dist: connect-python<0.6.0,>=0.5.0
Requires-Dist: protobuf>=4.21.0
Requires-Dist: httpx>=0.27.0
Requires-Dist: typing_extensions>=4.0.0
Requires-Dist: googleapis-common-protos>=1.70.0
Provides-Extra: dev
Requires-Dist: pytest>=7.0.0; extra == "dev"
Requires-Dist: pytest-asyncio>=0.21.0; extra == "dev"
Requires-Dist: black>=22.0.0; extra == "dev"
Requires-Dist: isort>=5.10.0; extra == "dev"
Requires-Dist: mypy>=1.0.0; extra == "dev"
Requires-Dist: flake8>=5.0.0; extra == "dev"
Provides-Extra: docs
Requires-Dist: sphinx>=5.0.0; extra == "docs"
Requires-Dist: sphinx-rtd-theme>=1.0.0; extra == "docs"
Dynamic: license-file
